njsscan/__init__.py
njsscan/__main__.py
njsscan/exceptions.py
njsscan/logger.py
njsscan/njsscan.py
njsscan/settings.py
njsscan/utils.py
njsscan/formatters/__init__.py
njsscan/formatters/cli.py
njsscan/formatters/defectdojo.py
njsscan/formatters/json_out.py
njsscan/formatters/sarif.py
njsscan/formatters/sonarqube.py
njsscan/rules/missing_controls.yaml
njsscan/rules/pattern_matcher/template_rules.yaml
njsscan/rules/semantic_grep/crypto/crypto_node.yaml
njsscan/rules/semantic_grep/crypto/timing_attack_node.yaml
njsscan/rules/semantic_grep/crypto/tls_node.yaml
njsscan/rules/semantic_grep/database/nosql_find_injection.yaml
njsscan/rules/semantic_grep/database/nosql_injection.yaml
njsscan/rules/semantic_grep/database/sequelize_tls.yaml
njsscan/rules/semantic_grep/database/sequelize_tls_validation.yaml
njsscan/rules/semantic_grep/database/sequelize_weak_tls.yaml
njsscan/rules/semantic_grep/database/sql_injection.yaml
njsscan/rules/semantic_grep/database/sql_injection_knex.yaml
njsscan/rules/semantic_grep/dos/express_bodyparser_dos.yaml
njsscan/rules/semantic_grep/dos/layer7_object_dos.yaml
njsscan/rules/semantic_grep/dos/regex_dos.yaml
njsscan/rules/semantic_grep/dos/regex_injection.yaml
njsscan/rules/semantic_grep/electronjs/security_electron.yaml
njsscan/rules/semantic_grep/eval/eval_deserialize.yaml
njsscan/rules/semantic_grep/eval/eval_grpc_deserialize.yaml
njsscan/rules/semantic_grep/eval/eval_node.yaml
njsscan/rules/semantic_grep/eval/eval_require.yaml
njsscan/rules/semantic_grep/eval/eval_sandbox.yaml
njsscan/rules/semantic_grep/eval/eval_vm2_injection.yaml
njsscan/rules/semantic_grep/eval/eval_vm_injection.yaml
njsscan/rules/semantic_grep/eval/eval_yaml_deserialize.yaml
njsscan/rules/semantic_grep/eval/server_side_template_injection.yaml
njsscan/rules/semantic_grep/exec/exec_os_command.yaml
njsscan/rules/semantic_grep/exec/exec_shelljs.yaml
njsscan/rules/semantic_grep/generic/error_disclosure.yaml
njsscan/rules/semantic_grep/generic/hardcoded_passport.yaml
cdmx_njsscan-1.0.2.dist-info/LICENSE
cdmx_njsscan-1.0.2.dist-info/METADATA
cdmx_njsscan-1.0.2.dist-info/WHEEL
cdmx_njsscan-1.0.2.dist-info/entry_points.txt
cdmx_njsscan-1.0.2.dist-info/top_level.txt
cdmx_njsscan-1.0.2.dist-info/RECORD
