Metadata-Version: 2.1
Name: cdmx-njsscan
Version: 1.0.2
Summary: njsscan is a SAST tool that can find insecure code patterns in your Node.js applications.
Home-page: https://github.com/cdmx1/njsscan
Author: Anonymous
Author-email: anonymous@example.com
Classifier: Development Status :: 4 - Beta
Classifier: Intended Audience :: Developers
Classifier: License :: OSI Approved :: GNU Lesser General Public License v3 or later (LGPLv3+)
Classifier: Programming Language :: Python :: 3.7
Requires-Python: >=3.8
License-File: LICENSE
Requires-Dist: colorama >=0.4.5
Requires-Dist: libsast >=3.1.4
Requires-Dist: semgrep >=1.86.0
Requires-Dist: sarif-om >=1.0.4
Requires-Dist: jschema-to-python >=1.2.3
Requires-Dist: tabulate >=0.8.10
